{
	"info": {
		"_postman_id": "43baff0d-8c37-4986-b86f-a826506c6997",
		"name": "Sistemas_corporativos",
		"schema": "https://schema.getpostman.com/json/collection/v2.1.0/collection.json",
		"_exporter_id": "34631135"
	},
	"item": [
		{
			"name": "User",
			"item": [
				{
					"name": "new1",
					"request": {
						"method": "POST",
						"header": [],
						"body": {
							"mode": "raw",
							"raw": "{\r\n    \"nome\": \"Jhonny Guimaraes\",\r\n    \"login\": \"jguimaraes\",\r\n    \"email\": \"jguimaraes@gmail.com\",\r\n    \"senha\": \"jg123\",\r\n    \"status\": \"ativo\"\r\n}",
							"options": {
								"raw": {
									"language": "json"
								}
							}
						},
						"url": {
							"raw": "http://localhost:3001/users/new",
							"protocol": "http",
							"host": [
								"localhost"
							],
							"port": "3001",
							"path": [
								"users",
								"new"
							]
						}
					},
					"response": []
				},
				{
					"name": "findAll",
					"protocolProfileBehavior": {
						"disableBodyPruning": true
					},
					"request": {
						"auth": {
							"type": "bearer",
							"bearer": [
								{
									"key": "token",
									"value": "eyJhbGciOiJIUzI1NiIsInR5cCI6IkpXVCJ9.eyJpZCI6MSwiaWF0IjoxNzE4MDYzNzkzLCJleHAiOjE3MTgwNjczOTN9.904NangvEnXrsOWVzGIx4We8_EtQONaceMwN9W5g_og",
									"type": "string"
								}
							]
						},
						"method": "GET",
						"header": [],
						"body": {
							"mode": "raw",
							"raw": "",
							"options": {
								"raw": {
									"language": "json"
								}
							}
						},
						"url": {
							"raw": "http://localhost:3001/users/findall",
							"protocol": "http",
							"host": [
								"localhost"
							],
							"port": "3001",
							"path": [
								"users",
								"findall"
							]
						}
					},
					"response": []
				},
				{
					"name": "login1",
					"request": {
						"auth": {
							"type": "bearer",
							"bearer": [
								{
									"key": "token",
									"value": "",
									"type": "string"
								}
							]
						},
						"method": "POST",
						"header": [],
						"body": {
							"mode": "raw",
							"raw": "{\r\n    \r\n    \"login\": \"ygg\",\r\n    \"senha\": \"ygg123\"\r\n}",
							"options": {
								"raw": {
									"language": "json"
								}
							}
						},
						"url": {
							"raw": "http://localhost:3001/users/login",
							"protocol": "http",
							"host": [
								"localhost"
							],
							"port": "3001",
							"path": [
								"users",
								"login"
							]
						}
					},
					"response": []
				},
				{
					"name": "findbyId",
					"request": {
						"method": "GET",
						"header": [],
						"url": {
							"raw": "http://localhost:3001/users/findbyId/1",
							"protocol": "http",
							"host": [
								"localhost"
							],
							"port": "3001",
							"path": [
								"users",
								"findbyId",
								"1"
							]
						}
					},
					"response": []
				},
				{
					"name": "update",
					"request": {
						"auth": {
							"type": "bearer",
							"bearer": [
								{
									"key": "token",
									"value": "eyJhbGciOiJIUzI1NiIsInR5cCI6IkpXVCJ9.eyJpZCI6MiwiaWF0IjoxNzE2ODE4MjQ5LCJleHAiOjE3MTY4MjE4NDl9.kaU-bHPcJoqhCvso-jBaTOtEqkqJed-Hy019Dh-slPw",
									"type": "string"
								}
							]
						},
						"method": "PUT",
						"header": [],
						"body": {
							"mode": "raw",
							"raw": "{\r\n    \"nome\":\"Yan Felipe G. Guimarães\"\r\n}",
							"options": {
								"raw": {
									"language": "json"
								}
							}
						},
						"url": {
							"raw": "http://localhost:3001/users//updateUser/2",
							"protocol": "http",
							"host": [
								"localhost"
							],
							"port": "3001",
							"path": [
								"users",
								"",
								"updateUser",
								"2"
							]
						}
					},
					"response": []
				},
				{
					"name": "login2",
					"request": {
						"auth": {
							"type": "bearer",
							"bearer": [
								{
									"key": "token",
									"value": "\"eyJhbGciOiJIUzI1NiIsInR5cCI6IkpXVCJ9.eyJpZCI6MSwiaWF0IjoxNzE5MzQwOTY1LCJleHAiOjE3MTkzNDQ1NjV9.-9akfmTatHMpe7cYC_e-wcvHWa1Pn7aMWyb37KxGpQQ",
									"type": "string"
								}
							]
						},
						"method": "POST",
						"header": [],
						"body": {
							"mode": "raw",
							"raw": "{\r\n    \"login\": \"jguimaraes\",\r\n    \"senha\": \"jg123\"\r\n}",
							"options": {
								"raw": {
									"language": "json"
								}
							}
						},
						"url": {
							"raw": "http://localhost:3001/users/login",
							"protocol": "http",
							"host": [
								"localhost"
							],
							"port": "3001",
							"path": [
								"users",
								"login"
							]
						}
					},
					"response": []
				},
				{
					"name": "new2",
					"request": {
						"method": "POST",
						"header": [],
						"body": {
							"mode": "raw",
							"raw": "{\r\n    \"nome\": \"Yan G. Guimaraes\",\r\n    \"login\": \"ygg\",\r\n    \"email\": \"ygg@gmail.com\",\r\n    \"senha\": \"ygg123\",\r\n    \"status\": \"ativo\"\r\n}",
							"options": {
								"raw": {
									"language": "json"
								}
							}
						},
						"url": {
							"raw": "http://localhost:3001/users/newUser",
							"protocol": "http",
							"host": [
								"localhost"
							],
							"port": "3001",
							"path": [
								"users",
								"newUser"
							]
						}
					},
					"response": []
				}
			]
		},
		{
			"name": "Cliente",
			"item": [
				{
					"name": "cliente/new",
					"request": {
						"auth": {
							"type": "bearer",
							"bearer": [
								{
									"key": "token",
									"value": "eyJhbGciOiJIUzI1NiIsInR5cCI6IkpXVCJ9.eyJpZCI6MSwiaWF0IjoxNzE5MTg3NzAxLCJleHAiOjE3MTkxOTEzMDF9.2EbzOP9toGY2WqgC0yWG4e0CrfcXVK1i_eIhuKaGoBw",
									"type": "string"
								}
							]
						},
						"method": "POST",
						"header": [],
						"body": {
							"mode": "raw",
							"raw": "{\r\n    \"nome\":\"jhonny guimaraes\",\r\n    \"CPF\":\"123.456.789-10\"\r\n}",
							"options": {
								"raw": {
									"language": "json"
								}
							}
						},
						"url": {
							"raw": "http://localhost:3001/cliente/new",
							"protocol": "http",
							"host": [
								"localhost"
							],
							"port": "3001",
							"path": [
								"cliente",
								"new"
							]
						}
					},
					"response": []
				}
			]
		},
		{
			"name": "Product",
			"item": [
				{
					"name": "findallproductbyid",
					"protocolProfileBehavior": {
						"disableBodyPruning": true
					},
					"request": {
						"method": "GET",
						"header": [],
						"body": {
							"mode": "raw",
							"raw": "",
							"options": {
								"raw": {
									"language": "json"
								}
							}
						},
						"url": {
							"raw": "http://localhost:3001/product/findallproductbyid/1",
							"protocol": "http",
							"host": [
								"localhost"
							],
							"port": "3001",
							"path": [
								"product",
								"findallproductbyid",
								"1"
							]
						}
					},
					"response": []
				},
				{
					"name": "/newproduct",
					"request": {
						"method": "POST",
						"header": [],
						"body": {
							"mode": "raw",
							"raw": "{\r\n    \"nome\": \"Iphone 14\",\r\n    \"descricao\": \"256 GB\",\r\n    \"status\": \"Ativo\"\r\n}",
							"options": {
								"raw": {
									"language": "json"
								}
							}
						},
						"url": {
							"raw": "http://localhost:3001/product/newproduct",
							"protocol": "http",
							"host": [
								"localhost"
							],
							"port": "3001",
							"path": [
								"product",
								"newproduct"
							]
						}
					},
					"response": []
				},
				{
					"name": "findallproduct",
					"request": {
						"method": "GET",
						"header": [],
						"url": {
							"raw": "http://localhost:3001/product/findallproduct",
							"protocol": "http",
							"host": [
								"localhost"
							],
							"port": "3001",
							"path": [
								"product",
								"findallproduct"
							]
						}
					},
					"response": []
				},
				{
					"name": "updateProduct",
					"request": {
						"method": "PUT",
						"header": [],
						"body": {
							"mode": "raw",
							"raw": "{\r\n    \"descricao\": \"64 GB\"\r\n}",
							"options": {
								"raw": {
									"language": "json"
								}
							}
						},
						"url": {
							"raw": "http://localhost:3001/product/updateProduct/1",
							"protocol": "http",
							"host": [
								"localhost"
							],
							"port": "3001",
							"path": [
								"product",
								"updateProduct",
								"1"
							]
						}
					},
					"response": []
				}
			]
		},
		{
			"name": "xtelefone",
			"item": [
				{
					"name": "new",
					"request": {
						"auth": {
							"type": "bearer",
							"bearer": [
								{
									"key": "token",
									"value": "eyJhbGciOiJIUzI1NiIsInR5cCI6IkpXVCJ9.eyJpZCI6MSwiaWF0IjoxNzE5MTc2NTMwLCJleHAiOjE3MTkxODAxMzB9.u06y1NOSZqFXxycIAaq9efgldGnZfHQ5fWRmI9_Dchg",
									"type": "string"
								}
							]
						},
						"method": "POST",
						"header": [],
						"body": {
							"mode": "raw",
							"raw": "{\r\n    \"DDD\":\"43\",\r\n    \"numero\": \"989797-8888\"\r\n}",
							"options": {
								"raw": {
									"language": "json"
								}
							}
						},
						"url": {
							"raw": "http://localhost:3001/xtelefone/new",
							"protocol": "http",
							"host": [
								"localhost"
							],
							"port": "3001",
							"path": [
								"xtelefone",
								"new"
							]
						}
					},
					"response": []
				},
				{
					"name": "findall",
					"request": {
						"auth": {
							"type": "noauth"
						},
						"method": "GET",
						"header": [],
						"url": {
							"raw": "http://localhost:3001/xtelefone/findall",
							"protocol": "http",
							"host": [
								"localhost"
							],
							"port": "3001",
							"path": [
								"xtelefone",
								"findall"
							]
						}
					},
					"response": []
				},
				{
					"name": "findbyId",
					"protocolProfileBehavior": {
						"disableBodyPruning": true
					},
					"request": {
						"method": "GET",
						"header": [],
						"body": {
							"mode": "raw",
							"raw": "",
							"options": {
								"raw": {
									"language": "json"
								}
							}
						},
						"url": {
							"raw": "http://localhost:3001/xtelefone/findbyId/1",
							"protocol": "http",
							"host": [
								"localhost"
							],
							"port": "3001",
							"path": [
								"xtelefone",
								"findbyId",
								"1"
							]
						}
					},
					"response": []
				},
				{
					"name": "update",
					"request": {
						"auth": {
							"type": "bearer",
							"bearer": [
								{
									"key": "token",
									"value": "eyJhbGciOiJIUzI1NiIsInR5cCI6IkpXVCJ9.eyJpZCI6MSwiaWF0IjoxNzE5MTc2NTMwLCJleHAiOjE3MTkxODAxMzB9.u06y1NOSZqFXxycIAaq9efgldGnZfHQ5fWRmI9_Dchg",
									"type": "string"
								}
							]
						},
						"method": "PUT",
						"header": [],
						"body": {
							"mode": "raw",
							"raw": "{\r\n    \"DDD\": 41\r\n}",
							"options": {
								"raw": {
									"language": "json"
								}
							}
						},
						"url": {
							"raw": "http://localhost:3001/xtelefone/update/1",
							"protocol": "http",
							"host": [
								"localhost"
							],
							"port": "3001",
							"path": [
								"xtelefone",
								"update",
								"1"
							]
						}
					},
					"response": []
				}
			]
		},
		{
			"name": "Deposit",
			"item": [
				{
					"name": "findById",
					"protocolProfileBehavior": {
						"disableBodyPruning": true
					},
					"request": {
						"method": "GET",
						"header": [],
						"body": {
							"mode": "raw",
							"raw": "",
							"options": {
								"raw": {
									"language": "json"
								}
							}
						},
						"url": {
							"raw": "http://localhost:3001/deposit/findabyid/2",
							"protocol": "http",
							"host": [
								"localhost"
							],
							"port": "3001",
							"path": [
								"deposit",
								"findabyid",
								"2"
							]
						}
					},
					"response": []
				},
				{
					"name": "findall",
					"request": {
						"method": "GET",
						"header": [],
						"url": {
							"raw": "http://localhost:3001/deposit/findall",
							"protocol": "http",
							"host": [
								"localhost"
							],
							"port": "3001",
							"path": [
								"deposit",
								"findall"
							]
						}
					},
					"response": []
				},
				{
					"name": "new",
					"request": {
						"auth": {
							"type": "bearer",
							"bearer": [
								{
									"key": "token",
									"value": "eyJhbGciOiJIUzI1NiIsInR5cCI6IkpXVCJ9.eyJpZCI6MSwiaWF0IjoxNzE5MTg3NzAxLCJleHAiOjE3MTkxOTEzMDF9.2EbzOP9toGY2WqgC0yWG4e0CrfcXVK1i_eIhuKaGoBw",
									"type": "string"
								}
							]
						},
						"method": "POST",
						"header": [],
						"body": {
							"mode": "raw",
							"raw": "{\r\n    \"central\": \"Ecoville\"\r\n    \r\n}",
							"options": {
								"raw": {
									"language": "json"
								}
							}
						},
						"url": {
							"raw": "http://localhost:3001/deposit/new",
							"protocol": "http",
							"host": [
								"localhost"
							],
							"port": "3001",
							"path": [
								"deposit",
								"new"
							]
						}
					},
					"response": []
				},
				{
					"name": "update",
					"request": {
						"method": "PUT",
						"header": [],
						"body": {
							"mode": "raw",
							"raw": "{\r\n    \"status\": \"true\"\r\n}",
							"options": {
								"raw": {
									"language": "json"
								}
							}
						},
						"url": {
							"raw": "http://localhost:3001/deposit/update/2",
							"protocol": "http",
							"host": [
								"localhost"
							],
							"port": "3001",
							"path": [
								"deposit",
								"update",
								"2"
							]
						}
					},
					"response": []
				}
			]
		},
		{
			"name": "ControleProduct",
			"item": [
				{
					"name": "new",
					"request": {
						"method": "POST",
						"header": [],
						"body": {
							"mode": "raw",
							"raw": "{\r\n\r\n    \"movimento_tipo\": \"entrada\",\r\n    \"qtd_disponivel\": 10,\r\n    \"qtd_bloqueado\": 0,\r\n    \"valor_faturado\": 0.0,\r\n    \"productId\": 1,\r\n    \"depositId\": 1\r\n         \r\n}",
							"options": {
								"raw": {
									"language": "json"
								}
							}
						},
						"url": {
							"raw": "http://localhost:3001/movementproduct/newmovement",
							"protocol": "http",
							"host": [
								"localhost"
							],
							"port": "3001",
							"path": [
								"movementproduct",
								"newmovement"
							]
						}
					},
					"response": []
				},
				{
					"name": "findall",
					"request": {
						"method": "GET",
						"header": [],
						"url": {
							"raw": "http://localhost:3001/controleproduct/findall",
							"protocol": "http",
							"host": [
								"localhost"
							],
							"port": "3001",
							"path": [
								"controleproduct",
								"findall"
							]
						}
					},
					"response": []
				},
				{
					"name": "findById/:id",
					"request": {
						"method": "GET",
						"header": [],
						"url": {
							"raw": "http://localhost:3001/controleproduct/findbyid/1",
							"protocol": "http",
							"host": [
								"localhost"
							],
							"port": "3001",
							"path": [
								"controleproduct",
								"findbyid",
								"1"
							]
						}
					},
					"response": []
				},
				{
					"name": "update/:id",
					"request": {
						"method": "PUT",
						"header": [],
						"body": {
							"mode": "raw",
							"raw": "{\r\n\r\n    \"movimento_tipo\": \"saida\",\r\n    \"qtd_disponivel\": 5,\r\n    \"qtd_bloqueado\": 5,\r\n    \"valor_faturado\": \"4500.0\"\r\n    \r\n         \r\n}",
							"options": {
								"raw": {
									"language": "json"
								}
							}
						},
						"url": {
							"raw": "http://localhost:3001/controleproduct/update/1",
							"protocol": "http",
							"host": [
								"localhost"
							],
							"port": "3001",
							"path": [
								"controleproduct",
								"update",
								"1"
							]
						}
					},
					"response": []
				},
				{
					"name": "getPosicaoByDeposito/:depositoId",
					"request": {
						"method": "GET",
						"header": [],
						"url": {
							"raw": "http://localhost:3001/controleproduct/getPosicaoByDeposito/1",
							"protocol": "http",
							"host": [
								"localhost"
							],
							"port": "3001",
							"path": [
								"controleproduct",
								"getPosicaoByDeposito",
								"1"
							]
						}
					},
					"response": []
				},
				{
					"name": "getPosicaoByProdutoDeposito/:produtoId/:depositoId",
					"request": {
						"method": "GET",
						"header": [],
						"url": {
							"raw": "http://localhost:3001/controleproduct/getPosicaoByProdutoDeposito/1/1",
							"protocol": "http",
							"host": [
								"localhost"
							],
							"port": "3001",
							"path": [
								"controleproduct",
								"getPosicaoByProdutoDeposito",
								"1",
								"1"
							]
						}
					},
					"response": []
				}
			]
		},
		{
			"name": "Cost Center",
			"item": [
				{
					"name": "new",
					"request": {
						"method": "POST",
						"header": [],
						"body": {
							"mode": "raw",
							"raw": "{\r\n    \r\n    \"codigo\":\"CCA01\",\r\n    \"departmentId\": 4\r\n    \r\n}\r\n",
							"options": {
								"raw": {
									"language": "json"
								}
							}
						},
						"url": {
							"raw": "http://localhost:3001/cost/new",
							"protocol": "http",
							"host": [
								"localhost"
							],
							"port": "3001",
							"path": [
								"cost",
								"new"
							]
						}
					},
					"response": []
				},
				{
					"name": "update/id",
					"request": {
						"method": "PUT",
						"header": [],
						"body": {
							"mode": "raw",
							"raw": "{\r\n  \r\n    \"departmentId\": 3\r\n\r\n}",
							"options": {
								"raw": {
									"language": "json"
								}
							}
						},
						"url": {
							"raw": "http://localhost:3001/cost/update/3",
							"protocol": "http",
							"host": [
								"localhost"
							],
							"port": "3001",
							"path": [
								"cost",
								"update",
								"3"
							]
						}
					},
					"response": []
				},
				{
					"name": "findall",
					"request": {
						"method": "GET",
						"header": [],
						"url": {
							"raw": "http://localhost:3001/cost/findall",
							"protocol": "http",
							"host": [
								"localhost"
							],
							"port": "3001",
							"path": [
								"cost",
								"findall"
							]
						}
					},
					"response": []
				},
				{
					"name": "findbyid/id",
					"request": {
						"method": "GET",
						"header": [],
						"url": {
							"raw": "http://localhost:3001/cost/findbyid/2",
							"protocol": "http",
							"host": [
								"localhost"
							],
							"port": "3001",
							"path": [
								"cost",
								"findbyid",
								"2"
							]
						}
					},
					"response": []
				},
				{
					"name": "delete/id",
					"request": {
						"method": "DELETE",
						"header": [],
						"body": {
							"mode": "raw",
							"raw": "",
							"options": {
								"raw": {
									"language": "json"
								}
							}
						},
						"url": {
							"raw": "http://localhost:3001/cost/delete/4",
							"protocol": "http",
							"host": [
								"localhost"
							],
							"port": "3001",
							"path": [
								"cost",
								"delete",
								"4"
							]
						}
					},
					"response": []
				}
			]
		},
		{
			"name": "Supplier",
			"item": [
				{
					"name": "update/id",
					"request": {
						"auth": {
							"type": "bearer",
							"bearer": [
								{
									"key": "token",
									"value": "eyJhbGciOiJIUzI1NiIsInR5cCI6IkpXVCJ9.eyJpZCI6MSwiaWF0IjoxNzE5MTg3NzAxLCJleHAiOjE3MTkxOTEzMDF9.2EbzOP9toGY2WqgC0yWG4e0CrfcXVK1i_eIhuKaGoBw",
									"type": "string"
								}
							]
						},
						"method": "PUT",
						"header": [],
						"body": {
							"mode": "raw",
							"raw": "{\r\n    \r\n    \"contato\": \"contato@megaeletronicos.com\"\r\n}",
							"options": {
								"raw": {
									"language": "json"
								}
							}
						},
						"url": {
							"raw": "http://localhost:3001/supplier/update/3",
							"protocol": "http",
							"host": [
								"localhost"
							],
							"port": "3001",
							"path": [
								"supplier",
								"update",
								"3"
							]
						}
					},
					"response": []
				},
				{
					"name": "new",
					"request": {
						"auth": {
							"type": "bearer",
							"bearer": [
								{
									"key": "token",
									"value": "eyJhbGciOiJIUzI1NiIsInR5cCI6IkpXVCJ9.eyJpZCI6MSwiaWF0IjoxNzE5MTg3NzAxLCJleHAiOjE3MTkxOTEzMDF9.2EbzOP9toGY2WqgC0yWG4e0CrfcXVK1i_eIhuKaGoBw",
									"type": "string"
								}
							]
						},
						"method": "POST",
						"header": [],
						"body": {
							"mode": "raw",
							"raw": "{\r\n    \"nome\":\"MegaEletronicos.py\",\r\n    \"cnpj\":\"41.695.877/0001-21\",\r\n    \"contato\": \"(045) 3528-9053 - (045) 3528-8462\",\r\n    \"natureza_operacao\": \"Importação\",\r\n    \"categoria\":\"Eletronico\"\r\n}",
							"options": {
								"raw": {
									"language": "json"
								}
							}
						},
						"url": {
							"raw": "http://localhost:3001/supplier/new",
							"protocol": "http",
							"host": [
								"localhost"
							],
							"port": "3001",
							"path": [
								"supplier",
								"new"
							]
						}
					},
					"response": []
				},
				{
					"name": "findall",
					"request": {
						"method": "GET",
						"header": [],
						"url": {
							"raw": "http://localhost:3001/supplier/findall",
							"protocol": "http",
							"host": [
								"localhost"
							],
							"port": "3001",
							"path": [
								"supplier",
								"findall"
							]
						}
					},
					"response": []
				},
				{
					"name": "findbyid/id",
					"request": {
						"method": "GET",
						"header": [],
						"url": {
							"raw": "http://localhost:3001/supplier/findbyid/2",
							"protocol": "http",
							"host": [
								"localhost"
							],
							"port": "3001",
							"path": [
								"supplier",
								"findbyid",
								"2"
							]
						}
					},
					"response": []
				}
			]
		},
		{
			"name": "Requisitions",
			"item": [
				{
					"name": "new",
					"request": {
						"auth": {
							"type": "bearer",
							"bearer": [
								{
									"key": "token",
									"value": "eyJhbGciOiJIUzI1NiIsInR5cCI6IkpXVCJ9.eyJpZCI6MSwiaWF0IjoxNzE5MDEyNzg0LCJleHAiOjE3MTkwMTM2ODR9.xECMJT6HnNSJ1mIpzdzZ06T8RKByQARApOyIbKsr024",
									"type": "string"
								}
							]
						},
						"method": "POST",
						"header": [],
						"body": {
							"mode": "raw",
							"raw": "{\r\n    \"produto_requerido\": \"Iphone 14 128 GB\",\r\n    \"qtd_requerida\": 1,\r\n    \"costCenterId\": 5,\r\n    \"natureza_operacao\": \"Importação\"\r\n    \r\n}",
							"options": {
								"raw": {
									"language": "json"
								}
							}
						},
						"url": {
							"raw": "http://localhost:3001/requisition/new",
							"protocol": "http",
							"host": [
								"localhost"
							],
							"port": "3001",
							"path": [
								"requisition",
								"new"
							]
						}
					},
					"response": []
				},
				{
					"name": "findall",
					"request": {
						"auth": {
							"type": "bearer",
							"bearer": [
								{
									"key": "token",
									"value": "eyJhbGciOiJIUzI1NiIsInR5cCI6IkpXVCJ9.eyJpZCI6MSwiaWF0IjoxNzE5MjY2MTA5LCJleHAiOjE3MTkyNjk3MDl9.l8QLVEPiC5XPtfXrnGWsZijYdKSyJzServ4nvExSIc0",
									"type": "string"
								}
							]
						},
						"method": "GET",
						"header": [],
						"url": {
							"raw": "http://localhost:3001/requisition/findall",
							"protocol": "http",
							"host": [
								"localhost"
							],
							"port": "3001",
							"path": [
								"requisition",
								"findall"
							]
						}
					},
					"response": []
				},
				{
					"name": "findbyid/id",
					"request": {
						"method": "GET",
						"header": [],
						"url": {
							"raw": "http://localhost:3001/requisition/findbyid/1",
							"protocol": "http",
							"host": [
								"localhost"
							],
							"port": "3001",
							"path": [
								"requisition",
								"findbyid",
								"1"
							]
						}
					},
					"response": []
				},
				{
					"name": "update/id",
					"request": {
						"method": "PUT",
						"header": [],
						"body": {
							"mode": "raw",
							"raw": "{\r\n    \"status\":\"pendente\"\r\n}",
							"options": {
								"raw": {
									"language": "json"
								}
							}
						},
						"url": {
							"raw": "http://localhost:3001/requisition/update/1",
							"protocol": "http",
							"host": [
								"localhost"
							],
							"port": "3001",
							"path": [
								"requisition",
								"update",
								"1"
							]
						}
					},
					"response": []
				},
				{
					"name": "getrequisitionbycostcenter/:id",
					"request": {
						"method": "GET",
						"header": [],
						"url": {
							"raw": "http://localhost:3001/requisition/getrequisitionbycostcenter/5",
							"protocol": "http",
							"host": [
								"localhost"
							],
							"port": "3001",
							"path": [
								"requisition",
								"getrequisitionbycostcenter",
								"5"
							]
						}
					},
					"response": []
				}
			]
		},
		{
			"name": "Department",
			"item": [
				{
					"name": "new",
					"request": {
						"auth": {
							"type": "bearer",
							"bearer": [
								{
									"key": "token",
									"value": "eyJhbGciOiJIUzI1NiIsInR5cCI6IkpXVCJ9.eyJpZCI6MSwiaWF0IjoxNzE5MTc2NTMwLCJleHAiOjE3MTkxODAxMzB9.u06y1NOSZqFXxycIAaq9efgldGnZfHQ5fWRmI9_Dchg",
									"type": "string"
								}
							]
						},
						"method": "POST",
						"header": [],
						"body": {
							"mode": "raw",
							"raw": "{\r\n    \"nome\": \"Manutenção\"\r\n}",
							"options": {
								"raw": {
									"language": "json"
								}
							}
						},
						"url": {
							"raw": "http://localhost:3001/department/new",
							"protocol": "http",
							"host": [
								"localhost"
							],
							"port": "3001",
							"path": [
								"department",
								"new"
							]
						}
					},
					"response": []
				},
				{
					"name": "findall",
					"request": {
						"method": "GET",
						"header": [],
						"url": {
							"raw": "http://localhost:3001/department/findall",
							"protocol": "http",
							"host": [
								"localhost"
							],
							"port": "3001",
							"path": [
								"department",
								"findall"
							]
						}
					},
					"response": []
				},
				{
					"name": "findbyid/id",
					"request": {
						"method": "GET",
						"header": [],
						"url": {
							"raw": "http://localhost:3001/department/finddepartmentbyid/2",
							"protocol": "http",
							"host": [
								"localhost"
							],
							"port": "3001",
							"path": [
								"department",
								"finddepartmentbyid",
								"2"
							]
						}
					},
					"response": []
				},
				{
					"name": "update/id",
					"request": {
						"method": "PUT",
						"header": [],
						"body": {
							"mode": "raw",
							"raw": "{\r\n    \"nome\": \"Vendas\"\r\n}",
							"options": {
								"raw": {
									"language": "json"
								}
							}
						},
						"url": {
							"raw": "http://localhost:3001/department/updatedepartment/3",
							"protocol": "http",
							"host": [
								"localhost"
							],
							"port": "3001",
							"path": [
								"department",
								"updatedepartment",
								"3"
							]
						}
					},
					"response": []
				}
			]
		},
		{
			"name": "Quotation",
			"item": [
				{
					"name": "findall",
					"request": {
						"method": "GET",
						"header": [],
						"url": {
							"raw": "http://localhost:3001/quotation/findall",
							"protocol": "http",
							"host": [
								"localhost"
							],
							"port": "3001",
							"path": [
								"quotation",
								"findall"
							]
						}
					},
					"response": []
				},
				{
					"name": "findbyid/id",
					"request": {
						"method": "GET",
						"header": [],
						"url": {
							"raw": "http://localhost:3001/quotation/findbyid/3",
							"protocol": "http",
							"host": [
								"localhost"
							],
							"port": "3001",
							"path": [
								"quotation",
								"findbyid",
								"3"
							]
						}
					},
					"response": []
				},
				{
					"name": "new",
					"request": {
						"method": "POST",
						"header": [],
						"body": {
							"mode": "raw",
							"raw": "{\r\n    \"quantidade\": 10,\r\n    \"custototal\": 665.00,\r\n    \"tipoPagamento\": \"ÁVISTA\",\r\n    \"supplierId\": 3,\r\n    \"quotationId\": 5\r\n    \r\n}",
							"options": {
								"raw": {
									"language": "json"
								}
							}
						},
						"url": {
							"raw": "http://localhost:3001/quotation/new",
							"protocol": "http",
							"host": [
								"localhost"
							],
							"port": "3001",
							"path": [
								"quotation",
								"new"
							]
						}
					},
					"response": []
				},
				{
					"name": "update/id",
					"request": {
						"auth": {
							"type": "bearer",
							"bearer": [
								{
									"key": "token",
									"value": "eyJhbGciOiJIUzI1NiIsInR5cCI6IkpXVCJ9.eyJpZCI6MSwiaWF0IjoxNzE5NjgyMDcwLCJleHAiOjE3MTk2ODU2NzB9.HhMZdSqBl9SlEKHJO8PKU_3NRJa_8EyN0xvFEHl1tzA",
									"type": "string"
								}
							]
						},
						"method": "PUT",
						"header": [],
						"body": {
							"mode": "raw",
							"raw": "{\r\n    \"preco\": 570.00\r\n    \r\n}",
							"options": {
								"raw": {
									"language": "json"
								}
							}
						},
						"url": {
							"raw": "http://localhost:3001/quotation/update/22",
							"protocol": "http",
							"host": [
								"localhost"
							],
							"port": "3001",
							"path": [
								"quotation",
								"update",
								"22"
							]
						}
					},
					"response": []
				},
				{
					"name": "findquotationsbysupplier",
					"request": {
						"method": "GET",
						"header": [],
						"url": {
							"raw": "http://localhost:3001/quotation/findquotationsbysupplier/1",
							"protocol": "http",
							"host": [
								"localhost"
							],
							"port": "3001",
							"path": [
								"quotation",
								"findquotationsbysupplier",
								"1"
							]
						}
					},
					"response": []
				},
				{
					"name": "findquotationsbyrequisition/1",
					"protocolProfileBehavior": {
						"disableBodyPruning": true
					},
					"request": {
						"method": "GET",
						"header": [],
						"body": {
							"mode": "raw",
							"raw": "",
							"options": {
								"raw": {
									"language": "json"
								}
							}
						},
						"url": {
							"raw": "http://localhost:3001/quotation/findquotationsbyrequisition/1",
							"protocol": "http",
							"host": [
								"localhost"
							],
							"port": "3001",
							"path": [
								"quotation",
								"findquotationsbyrequisition",
								"1"
							]
						}
					},
					"response": []
				}
			]
		},
		{
			"name": "Purchase",
			"item": [
				{
					"name": "new",
					"request": {
						"auth": {
							"type": "bearer",
							"bearer": [
								{
									"key": "token",
									"value": "eyJhbGciOiJIUzI1NiIsInR5cCI6IkpXVCJ9.eyJpZCI6MSwiaWF0IjoxNzE4OTI5ODg5LCJleHAiOjE3MTg5MzM0ODl9.1jElP2yb2SYWEITWtvgjqCtWys0ctQMh08-LrkcC1FM",
									"type": "string"
								}
							]
						},
						"method": "POST",
						"header": [],
						"body": {
							"mode": "raw",
							"raw": "{\r\n   \"quantidade\": 10,\r\n   \"custototal\": 6650.00,\r\n   \"tipoPagamento\": \"PARCELADO\",\r\n   \"quotationId\": 5\r\n   \r\n}",
							"options": {
								"raw": {
									"language": "json"
								}
							}
						},
						"url": {
							"raw": "http://localhost:3001/purchase/new",
							"protocol": "http",
							"host": [
								"localhost"
							],
							"port": "3001",
							"path": [
								"purchase",
								"new"
							]
						}
					},
					"response": []
				},
				{
					"name": "findall",
					"request": {
						"auth": {
							"type": "bearer",
							"bearer": [
								{
									"key": "token",
									"value": "eyJhbGciOiJIUzI1NiIsInR5cCI6IkpXVCJ9.eyJpZCI6MSwiaWF0IjoxNzE4NjcxNTMyLCJleHAiOjE3MTg2NzUxMzJ9.EFWQg_9LL_zBEFXEIDROClCU6FBKqEmCfNeEFI6tYD0",
									"type": "string"
								}
							]
						},
						"method": "GET",
						"header": [],
						"url": {
							"raw": "http://localhost:3001/purchase/findall",
							"protocol": "http",
							"host": [
								"localhost"
							],
							"port": "3001",
							"path": [
								"purchase",
								"findall"
							]
						}
					},
					"response": []
				},
				{
					"name": "findbyid/:id",
					"request": {
						"method": "GET",
						"header": [],
						"url": {
							"raw": "http://localhost:3001/purchase/findpurchasebyid/3",
							"protocol": "http",
							"host": [
								"localhost"
							],
							"port": "3001",
							"path": [
								"purchase",
								"findpurchasebyid",
								"3"
							]
						}
					},
					"response": []
				},
				{
					"name": "update/:id",
					"request": {
						"method": "PUT",
						"header": [],
						"body": {
							"mode": "raw",
							"raw": "{\r\n   \"quantidade\": 10\r\n  \r\n}",
							"options": {
								"raw": {
									"language": "json"
								}
							}
						},
						"url": {
							"raw": "http://localhost:3001/purchase/updatepurchase/3",
							"protocol": "http",
							"host": [
								"localhost"
							],
							"port": "3001",
							"path": [
								"purchase",
								"updatepurchase",
								"3"
							]
						}
					},
					"response": []
				}
			]
		},
		{
			"name": "Sales",
			"item": [
				{
					"name": "findsalesbyid/id",
					"request": {
						"method": "GET",
						"header": [],
						"url": {
							"raw": "http://localhost:3001/sales/findsalesbyid/2",
							"protocol": "http",
							"host": [
								"localhost"
							],
							"port": "3001",
							"path": [
								"sales",
								"findsalesbyid",
								"2"
							]
						}
					},
					"response": []
				},
				{
					"name": "newsales",
					"request": {
						"method": "POST",
						"header": [],
						"body": {
							"mode": "raw",
							"raw": "{\r\n    \"qtdVendida\": 1,\r\n    \"custoUnitario\": 780.00,\r\n    \"parcelas\": 10,\r\n    \"numeroNotaFiscal\": \"520\",\r\n    \"productId\":1  \r\n}",
							"options": {
								"raw": {
									"language": "json"
								}
							}
						},
						"url": {
							"raw": "http://localhost:3001/sales/newsales",
							"protocol": "http",
							"host": [
								"localhost"
							],
							"port": "3001",
							"path": [
								"sales",
								"newsales"
							]
						}
					},
					"response": []
				},
				{
					"name": "findallsales",
					"request": {
						"method": "GET",
						"header": [],
						"url": {
							"raw": "http://localhost:3001/sales/findallsales",
							"protocol": "http",
							"host": [
								"localhost"
							],
							"port": "3001",
							"path": [
								"sales",
								"findallsales"
							]
						}
					},
					"response": []
				},
				{
					"name": "updatesales/id",
					"request": {
						"method": "PUT",
						"header": [],
						"body": {
							"mode": "raw",
							"raw": "{\r\n    \"qtdVendida\": 2\r\n}",
							"options": {
								"raw": {
									"language": "json"
								}
							}
						},
						"url": {
							"raw": "http://localhost:3001/sales//updatesales/2",
							"protocol": "http",
							"host": [
								"localhost"
							],
							"port": "3001",
							"path": [
								"sales",
								"",
								"updatesales",
								"2"
							]
						}
					},
					"response": []
				}
			]
		},
		{
			"name": "Title",
			"item": [
				{
					"name": "newtitle",
					"request": {
						"method": "POST",
						"header": [],
						"body": {
							"mode": "raw",
							"raw": "{\r\n    \"numeroNotaFiscal\": \"520\",\r\n    \"numeroParcela\": 1,\r\n    \"valorOriginal\": 78.00,\r\n    \"dataVencimento\" : \"2024-06-27 16:05:01\",\r\n    \"situacao\": \"pendente\"\r\n}",
							"options": {
								"raw": {
									"language": "json"
								}
							}
						},
						"url": {
							"raw": "http://localhost:3001/title/newtitle",
							"protocol": "http",
							"host": [
								"localhost"
							],
							"port": "3001",
							"path": [
								"title",
								"newtitle"
							]
						}
					},
					"response": []
				},
				{
					"name": "findalltitle",
					"request": {
						"method": "GET",
						"header": [],
						"url": {
							"raw": "http://localhost:3001/title/findalltitle",
							"protocol": "http",
							"host": [
								"localhost"
							],
							"port": "3001",
							"path": [
								"title",
								"findalltitle"
							]
						}
					},
					"response": []
				},
				{
					"name": "updatetitle/id",
					"request": {
						"method": "PUT",
						"header": [],
						"body": {
							"mode": "raw",
							"raw": "{\r\n    \"situacao\":\"pago\"\r\n}",
							"options": {
								"raw": {
									"language": "json"
								}
							}
						},
						"url": {
							"raw": "http://localhost:3001/title/updatetitle/1",
							"protocol": "http",
							"host": [
								"localhost"
							],
							"port": "3001",
							"path": [
								"title",
								"updatetitle",
								"1"
							]
						}
					},
					"response": []
				},
				{
					"name": "findtitlebyid/id",
					"request": {
						"method": "GET",
						"header": [],
						"url": {
							"raw": "http://localhost:3001/title/findtitlebyid/1",
							"protocol": "http",
							"host": [
								"localhost"
							],
							"port": "3001",
							"path": [
								"title",
								"findtitlebyid",
								"1"
							]
						}
					},
					"response": []
				}
			]
		},
		{
			"name": "ControleTitles",
			"item": [
				{
					"name": "newcontrole",
					"request": {
						"method": "POST",
						"header": [],
						"body": {
							"mode": "raw",
							"raw": "{\r\n    \"tipoMovimento\": \"abertura\",\r\n    \"valorMovimento\": 78.00,\r\n    \"valorMulta\": 0,\r\n    \"valorJuros\": 0,\r\n    \"titleId\": 1\r\n    \r\n}",
							"options": {
								"raw": {
									"language": "json"
								}
							}
						},
						"url": {
							"raw": "http://localhost:3001/controletitle/newcontrole",
							"protocol": "http",
							"host": [
								"localhost"
							],
							"port": "3001",
							"path": [
								"controletitle",
								"newcontrole"
							]
						}
					},
					"response": []
				},
				{
					"name": "findallcontrole",
					"request": {
						"method": "GET",
						"header": [],
						"url": {
							"raw": "http://localhost:3001/controletitle/findallcontrole",
							"protocol": "http",
							"host": [
								"localhost"
							],
							"port": "3001",
							"path": [
								"controletitle",
								"findallcontrole"
							]
						}
					},
					"response": []
				},
				{
					"name": "findallcontrolebyid/id",
					"request": {
						"method": "GET",
						"header": [],
						"url": {
							"raw": "http://localhost:3001/controletitle/findallcontrolebyid/1",
							"protocol": "http",
							"host": [
								"localhost"
							],
							"port": "3001",
							"path": [
								"controletitle",
								"findallcontrolebyid",
								"1"
							]
						}
					},
					"response": []
				},
				{
					"name": "updatecontole/id",
					"request": {
						"auth": {
							"type": "bearer",
							"bearer": [
								{
									"key": "token",
									"value": "eyJhbGciOiJIUzI1NiIsInR5cCI6IkpXVCJ9.eyJpZCI6MSwiaWF0IjoxNzE5NjkzNTUzLCJleHAiOjE3MTk2OTcxNTN9.N4u6RdCgBhhMhWLx4pOaUaW7WmPMU1qMd7_gxnNlL8E",
									"type": "string"
								}
							]
						},
						"method": "PUT",
						"header": [],
						"body": {
							"mode": "raw",
							"raw": "{\r\n    \"valorParcial\": 2000,\r\n    \"dataPagamento\": \"2024-08-01 21:00:00\"\r\n}",
							"options": {
								"raw": {
									"language": "json"
								}
							}
						},
						"url": {
							"raw": "http://localhost:3001/controletitle/update/30",
							"protocol": "http",
							"host": [
								"localhost"
							],
							"port": "3001",
							"path": [
								"controletitle",
								"update",
								"30"
							]
						}
					},
					"response": []
				}
			]
		},
		{
			"name": "NotafIscals",
			"item": [
				{
					"name": "http://localhost:3001/notafiscal/new",
					"protocolProfileBehavior": {
						"disableBodyPruning": true
					},
					"request": {
						"method": "GET",
						"header": [],
						"body": {
							"mode": "raw",
							"raw": "{\r\n    \"nome_razao\": \r\n}",
							"options": {
								"raw": {
									"language": "json"
								}
							}
						},
						"url": {
							"raw": "http://localhost:3001/notafiscal/new",
							"protocol": "http",
							"host": [
								"localhost"
							],
							"port": "3001",
							"path": [
								"notafiscal",
								"new"
							]
						}
					},
					"response": []
				}
			]
		},
		{
			"name": "Processos",
			"item": [
				{
					"name": "/purchaseprocess/new",
					"request": {
						"auth": {
							"type": "bearer",
							"bearer": [
								{
									"key": "token",
									"value": "eyJhbGciOiJIUzI1NiIsInR5cCI6IkpXVCJ9.eyJpZCI6MSwiaWF0IjoxNzE5NjgyMDcwLCJleHAiOjE3MTk2ODU2NzB9.HhMZdSqBl9SlEKHJO8PKU_3NRJa_8EyN0xvFEHl1tzA",
									"type": "string"
								}
							]
						},
						"method": "POST",
						"header": [],
						"body": {
							"mode": "raw",
							"raw": "{\r\n   \r\n   \"tipoPagamento\": \"2X\",\r\n   \"quotationId\": 23\r\n   \r\n}",
							"options": {
								"raw": {
									"language": "json"
								}
							}
						},
						"url": {
							"raw": "http://localhost:3001/purchaseprocessing/new",
							"protocol": "http",
							"host": [
								"localhost"
							],
							"port": "3001",
							"path": [
								"purchaseprocessing",
								"new"
							]
						}
					},
					"response": []
				},
				{
					"name": "departmentprocessing/new",
					"request": {
						"auth": {
							"type": "bearer",
							"bearer": [
								{
									"key": "token",
									"value": "eyJhbGciOiJIUzI1NiIsInR5cCI6IkpXVCJ9.eyJpZCI6MSwiaWF0IjoxNzE5MTg3NzAxLCJleHAiOjE3MTkxOTEzMDF9.2EbzOP9toGY2WqgC0yWG4e0CrfcXVK1i_eIhuKaGoBw",
									"type": "string"
								}
							]
						},
						"method": "POST",
						"header": [],
						"body": {
							"mode": "raw",
							"raw": "{\r\n    \"nome\": \"Administração\"\r\n}",
							"options": {
								"raw": {
									"language": "json"
								}
							}
						},
						"url": {
							"raw": "http://localhost:3001/departmentprocessing/new",
							"protocol": "http",
							"host": [
								"localhost"
							],
							"port": "3001",
							"path": [
								"departmentprocessing",
								"new"
							]
						}
					},
					"response": []
				},
				{
					"name": "/requisitionprocessing/new",
					"request": {
						"auth": {
							"type": "bearer",
							"bearer": [
								{
									"key": "token",
									"value": "eyJhbGciOiJIUzI1NiIsInR5cCI6IkpXVCJ9.eyJpZCI6MSwiaWF0IjoxNzE5Njk3MjAwLCJleHAiOjE3MTk3MDA4MDB9.7GwibC6VZZHztL-bcx0kXfoEN7f-EOHOfhY_j1ndDY8",
									"type": "string"
								}
							]
						},
						"method": "POST",
						"header": [],
						"body": {
							"mode": "raw",
							"raw": "{\r\n    \"produto_requerido\": \"Iphone 13 128 GB\",\r\n    \"qtd_requerida\": 1,\r\n    \"categoria\":\"Eletronico\",\r\n    \"costCenterId\": 2,\r\n    \"natureza_operacao\": \"Venda\",\r\n    \"tipoPagamento\":\"1X\"\r\n    \r\n}",
							"options": {
								"raw": {
									"language": "json"
								}
							}
						},
						"url": {
							"raw": "http://localhost:3001/requisitionprocessing/new",
							"protocol": "http",
							"host": [
								"localhost"
							],
							"port": "3001",
							"path": [
								"requisitionprocessing",
								"new"
							]
						}
					},
					"response": []
				},
				{
					"name": "sellprocessing/new",
					"request": {
						"auth": {
							"type": "bearer",
							"bearer": [
								{
									"key": "token",
									"value": "eyJhbGciOiJIUzI1NiIsInR5cCI6IkpXVCJ9.eyJpZCI6MSwiaWF0IjoxNzE5Njk3MjAwLCJleHAiOjE3MTk3MDA4MDB9.7GwibC6VZZHztL-bcx0kXfoEN7f-EOHOfhY_j1ndDY8",
									"type": "string"
								}
							]
						},
						"method": "POST",
						"header": [],
						"body": {
							"mode": "raw",
							"raw": "{\r\n    \"requisitionId\":23,\r\n    \"tipoPagamento\":\"1X\"\r\n    \r\n}",
							"options": {
								"raw": {
									"language": "json"
								}
							}
						},
						"url": {
							"raw": "http://localhost:3001/sellprocessing/new",
							"protocol": "http",
							"host": [
								"localhost"
							],
							"port": "3001",
							"path": [
								"sellprocessing",
								"new"
							]
						}
					},
					"response": []
				},
				{
					"name": "/titlepay/pagarparcial",
					"request": {
						"auth": {
							"type": "bearer",
							"bearer": [
								{
									"key": "token",
									"value": "eyJhbGciOiJIUzI1NiIsInR5cCI6IkpXVCJ9.eyJpZCI6MSwiaWF0IjoxNzE5NzA0Njk0LCJleHAiOjE3MTk3MDgyOTR9.L5Ni8wd-d2rNi3zxjuVlEIzichF7mAgwAzv9UNpbafc",
									"type": "string"
								}
							]
						},
						"method": "PUT",
						"header": [],
						"body": {
							"mode": "raw",
							"raw": "{ \r\n    \"cpf_cnpj\": \"123456/0001-10\",\r\n    \"valor\": 725\r\n}",
							"options": {
								"raw": {
									"language": "json"
								}
							}
						},
						"url": {
							"raw": "http://localhost:3001/titlepay/pagarparcial",
							"protocol": "http",
							"host": [
								"localhost"
							],
							"port": "3001",
							"path": [
								"titlepay",
								"pagarparcial"
							]
						}
					},
					"response": []
				},
				{
					"name": "/pagarintegral",
					"request": {
						"method": "PUT",
						"header": [],
						"url": {
							"raw": "http://localhost:3001/titlepay/pagarintegral",
							"protocol": "http",
							"host": [
								"localhost"
							],
							"port": "3001",
							"path": [
								"titlepay",
								"pagarintegral"
							]
						}
					},
					"response": []
				}
			]
		}
	]
}